<?xml version="1.0" standalone="yes"?>
<words>
  <word>exact</word>
  <word>superb</word>
  <word>genuine</word>
  <word>absolutely</word>
  <word>adorable</word>
  <word>accepted</word>
  <word>acclaimed</word>
  <word>accomplish</word>
  <word>accomplishment</word>
  <word>achievement</word>
  <word>action</word>
  <word>active</word>
  <word>admire</word>
  <word>adventure</word>
  <word>affirmative</word>
  <word>affluent</word>
  <word>agree</word>
  <word>agreeable</word>
  <word>amazing</word>
  <word>angelic</word>
  <word>appealing</word>
  <word>approve</word>
  <word>aptitude</word>
  <word>attractive</word>
  <word>awesome</word>
  <word>beaming</word>
  <word>beautiful</word>
  <word>believe</word>
  <word>beneficial</word>
  <word>bliss</word>
  <word>bountiful</word>
  <word>bounty</word>
  <word>brave</word>
  <word>bravo</word>
  <word>brilliant</word>
  <word>bubbly</word>
  <word>calm</word>
  <word>celebrated</word>
  <word>certain</word>
  <word>champ</word>
  <word>champion</word>
  <word>charming</word>
  <word>cheery</word>
  <word>choice</word>
  <word>classic</word>
  <word>classical</word>
  <word>clean</word>
  <word>commend</word>
  <word>composed</word>
  <word>congratulation</word>
  <word>constant</word>
  <word>cool</word>
  <word>courageous</word>
  <word>creative</word>
  <word>cute</word>
  <word>dazzling</word>
  <word>delight</word>
  <word>delightful</word>
  <word>distinguished</word>
  <word>divine</word>
  <word>earnest</word>
  <word>easy</word>
  <word>ecstatic</word>
  <word>effective</word>
  <word>effervescent</word>
  <word>efficient</word>
  <word>effortless</word>
  <word>electrifying</word>
  <word>elegant</word>
  <word>enchanting</word>
  <word>encouraging</word>
  <word>endorsed</word>
  <word>energetic</word>
  <word>energized</word>
  <word>engaging</word>
  <word>enthusiastic</word>
  <word>essential</word>
  <word>esteemed</word>
  <word>ethical</word>
  <word>excellent</word>
  <word>exciting</word>
  <word>exquisite</word>
  <word>fabulous</word>
  <word>fair</word>
  <word>familiar</word>
  <word>famous</word>
  <word>fantastic</word>
  <word>favorable</word>
  <word>fetching</word>
  <word>fine</word>
  <word>fitting</word>
  <word>flourishing</word>
  <word>fortunate</word>
  <word>free</word>
  <word>fresh</word>
  <word>friendly</word>
  <word>fun</word>
  <word>funny</word>
  <word>generous</word>
  <word>genius</word>
  <word>genuine</word>
  <word>giving</word>
  <word>glamorous</word>
  <word>glowing</word>
  <word>good</word>
  <word>gorgeous</word>
  <word>graceful</word>
  <word>great</word>
  <word>green</word>
  <word>grin</word>
  <word>growing</word>
  <word>handsome</word>
  <word>happy</word>
  <word>harmonious</word>
  <word>healing</word>
  <word>healthy</word>
  <word>hearty</word>
  <word>heavenly</word>
  <word>honest</word>
  <word>honorable</word>
  <word>honored</word>
  <word>hug</word>
  <word>idea</word>
  <word>ideal</word>
  <word>imaginative</word>
  <word>imagine</word>
  <word>impressive</word>
  <word>independent</word>
  <word>innovate</word>
  <word>innovative</word>
  <word>instant</word>
  <word>instantaneous</word>
  <word>instinctive</word>
  <word>intuitive</word>
  <word>intellectual</word>
  <word>intelligent</word>
  <word>inventive</word>
  <word>jovial</word>
  <word>joy</word>
  <word>jubilant</word>
  <word>keen</word>
  <word>kind</word>
  <word>knowing</word>
  <word>knowledgeable</word>
  <word>laugh</word>
  <word>legendary</word>
  <word>light</word>
  <word>learned</word>
  <word>lively</word>
  <word>lovely</word>
  <word>lucid</word>
  <word>lucky</word>
  <word>luminous</word>
  <word>marvelous</word>
  <word>masterful</word>
  <word>meaningful</word>
  <word>merit</word>
  <word>meritorious</word>
  <word>miraculous</word>
  <word>motivating</word>
  <word>moving</word>
  <word>natural</word>
  <word>nice</word>
  <word>novel</word>
  <word>now</word>
  <word>nurturing</word>
  <word>nutritious</word>
  <word>okay</word>
  <word>one</word>
  <word>one-hundred percent</word>
  <word>open</word>
  <word>optimistic</word>
  <word>paradise</word>
  <word>perfect</word>
  <word>phenomenal</word>
  <word>pleasurable</word>
  <word>plentiful</word>
  <word>pleasant</word>
  <word>poised</word>
  <word>polished</word>
  <word>popular</word>
  <word>positive</word>
  <word>powerful</word>
  <word>prepared</word>
  <word>pretty</word>
  <word>principled</word>
  <word>productive</word>
  <word>progress</word>
  <word>prominent</word>
  <word>protected</word>
  <word>proud</word>
  <word>quality</word>
  <word>quick</word>
  <word>quiet</word>
  <word>ready</word>
  <word>reassuring</word>
  <word>refined</word>
  <word>refreshing</word>
  <word>rejoice</word>
  <word>reliable</word>
  <word>remarkable</word>
  <word>resounding</word>
  <word>respected</word>
  <word>restored</word>
  <word>reward</word>
  <word>rewarding</word>
  <word>right</word>
  <word>robust</word>
  <word>safe</word>
  <word>satisfactory</word>
  <word>secure</word>
  <word>seemly</word>
  <word>simple</word>
  <word>skilled</word>
  <word>skillful</word>
  <word>smile</word>
  <word>soulful</word>
  <word>sparkling</word>
  <word>special</word>
  <word>spirited</word>
  <word>spiritual</word>
  <word>stirring</word>
  <word>stupendous</word>
  <word>stunning</word>
  <word>success</word>
  <word>successful</word>
  <word>sunny</word>
  <word>super</word>
  <word>superb</word>
  <word>supporting</word>
  <word>surprising</word>
  <word>terrific</word>
  <word>thorough</word>
  <word>thrilling</word>
  <word>thriving</word>
  <word>tops</word>
  <word>tranquil</word>
  <word>transforming</word>
  <word>transformative</word>
  <word>trusting</word>
  <word>truthful</word>
  <word>unreal</word>
  <word>unwavering</word>
  <word>up</word>
  <word>upbeat</word>
  <word>upright</word>
  <word>upstanding</word>
  <word>valued</word>
  <word>vibrant</word>
  <word>victorious</word>
  <word>victory</word>
  <word>vigorous</word>
  <word>virtuous</word>
  <word>vital</word>
  <word>vivacious</word>
  <word>wealthy</word>
  <word>welcome</word>
  <word>well</word>
  <word>whole</word>
  <word>wholesome</word>
  <word>willing</word>
  <word>wonderful</word>
  <word>wondrous</word>
  <word>worthy</word>
  <word>wow</word>
  <word>yes</word>
  <word>yummy</word>
  <word>zeal</word>
  <word>gud</word>
  <word>superb</word>
  <word>thank</word>
  <word>thanks</word>
  <word>best</word>
  <word>abound</word>
  <word>abounds</word>
  <word>abundance</word>
  <word>abundant</word>
  <word>accessable</word>
  <word>accessible</word>
  <word>acclaim</word>
  <word>acclaimed</word>
  <word>acclamation</word>
  <word>accolade</word>
  <word>accolades</word>
  <word>accommodative</word>
  <word>accomodative</word>
  <word>accomplish</word>
  <word>accomplished</word>
  <word>accomplishment</word>
  <word>accomplishments</word>
  <word>accurate</word>
  <word>accurately</word>
  <word>achievable</word>
  <word>achievement</word>
  <word>achievements</word>
  <word>achievible</word>
  <word>acumen</word>
  <word>adaptable</word>
  <word>adaptive</word>
  <word>adequate</word>
  <word>adjustable</word>
  <word>admirable</word>
  <word>admirably</word>
  <word>admiration</word>
  <word>admire</word>
  <word>admirer</word>
  <word>admiring</word>
  <word>admiringly</word>
  <word>adorable</word>
  <word>adore</word>
  <word>adored</word>
  <word>adorer</word>
  <word>adoring</word>
  <word>adoringly</word>
  <word>adroit</word>
  <word>adroitly</word>
  <word>adulate</word>
  <word>adulation</word>
  <word>adulatory</word>
  <word>advanced</word>
  <word>advantage</word>
  <word>advantageous</word>
  <word>advantageously</word>
  <word>advantages</word>
  <word>adventuresome</word>
  <word>adventurous</word>
  <word>advocate</word>
  <word>advocated</word>
  <word>advocates</word>
  <word>affability</word>
  <word>affable</word>
  <word>affably</word>
  <word>affectation</word>
  <word>affection</word>
  <word>affectionate</word>
  <word>affinity</word>
  <word>affirm</word>
  <word>affirmation</word>
  <word>affirmative</word>
  <word>affluence</word>
  <word>affluent</word>
  <word>afford</word>
  <word>affordable</word>
  <word>affordably</word>
  <word>afordable</word>
  <word>agile</word>
  <word>agilely</word>
  <word>agility</word>
  <word>agreeable</word>
  <word>agreeableness</word>
  <word>agreeably</word>
  <word>all-around</word>
  <word>alluring</word>
  <word>alluringly</word>
  <word>altruistic</word>
  <word>altruistically</word>
  <word>amaze</word>
  <word>amazed</word>
  <word>amazement</word>
  <word>amazes</word>
  <word>amazing</word>
  <word>amazingly</word>
  <word>ambitious</word>
  <word>ambitiously</word>
  <word>ameliorate</word>
  <word>amenable</word>
  <word>amenity</word>
  <word>amiability</word>
  <word>amiabily</word>
  <word>amiable</word>
  <word>amicability</word>
  <word>amicable</word>
  <word>amicably</word>
  <word>amity</word>
  <word>ample</word>
  <word>amply</word>
  <word>amuse</word>
  <word>amusing</word>
  <word>amusingly</word>
  <word>angel</word>
  <word>angelic</word>
  <word>apotheosis</word>
  <word>appeal</word>
  <word>appealing</word>
  <word>applaud</word>
  <word>appreciable</word>
  <word>appreciate</word>
  <word>appreciated</word>
  <word>appreciates</word>
  <word>appreciative</word>
  <word>appreciatively</word>
  <word>appropriate</word>
  <word>approval</word>
  <word>approve</word>
  <word>ardent</word>
  <word>ardently</word>
  <word>ardor</word>
  <word>articulate</word>
  <word>aspiration</word>
  <word>aspirations</word>
  <word>aspire</word>
  <word>assurance</word>
  <word>assurances</word>
  <word>assure</word>
  <word>assuredly</word>
  <word>assuring</word>
  <word>astonish</word>
  <word>astonished</word>
  <word>astonishing</word>
  <word>astonishingly</word>
  <word>astonishment</word>
  <word>astound</word>
  <word>astounded</word>
  <word>astounding</word>
  <word>astoundingly</word>
  <word>astutely</word>
  <word>attentive</word>
  <word>attraction</word>
  <word>attractive</word>
  <word>attractively</word>
  <word>attune</word>
  <word>audible</word>
  <word>audibly</word>
  <word>auspicious</word>
  <word>authentic</word>
  <word>authoritative</word>
  <word>autonomous</word>
  <word>available</word>
  <word>aver</word>
  <word>avid</word>
  <word>avidly</word>
  <word>award</word>
  <word>awarded</word>
  <word>awards</word>
  <word>awe</word>
  <word>awed</word>
  <word>awesome</word>
  <word>awesomely</word>
  <word>awesomeness</word>
  <word>awestruck</word>
  <word>awsome</word>
  <word>backbone</word>
  <word>balanced</word>
  <word>bargain</word>
  <word>beauteous</word>
  <word>beautiful</word>
  <word>beautifullly</word>
  <word>beautifully</word>
  <word>beautify</word>
  <word>beauty</word>
  <word>beckon</word>
  <word>beckoned</word>
  <word>beckoning</word>
  <word>beckons</word>
  <word>believable</word>
  <word>believeable</word>
  <word>beloved</word>
  <word>benefactor</word>
  <word>beneficent</word>
  <word>beneficial</word>
  <word>beneficially</word>
  <word>beneficiary</word>
  <word>benefit</word>
  <word>benefits</word>
  <word>benevolence</word>
  <word>benevolent</word>
  <word>benifits</word>
  <word>best</word>
  <word>best-known</word>
  <word>best-performing</word>
  <word>best-selling</word>
  <word>better</word>
  <word>better-known</word>
  <word>better-than-expected</word>
  <word>beutifully</word>
  <word>blameless</word>
  <word>bless</word>
  <word>blessing</word>
  <word>bliss</word>
  <word>blissful</word>
  <word>blissfully</word>
  <word>blithe</word>
  <word>blockbuster</word>
  <word>bloom</word>
  <word>blossom</word>
  <word>bolster</word>
  <word>bonny</word>
  <word>bonus</word>
  <word>bonuses</word>
  <word>boom</word>
  <word>booming</word>
  <word>boost</word>
  <word>boundless</word>
  <word>bountiful</word>
  <word>brainiest</word>
  <word>brainy</word>
  <word>brand-new</word>
  <word>brave</word>
  <word>bravery</word>
  <word>bravo</word>
  <word>breakthrough</word>
  <word>breakthroughs</word>
  <word>breathlessness</word>
  <word>breathtaking</word>
  <word>breathtakingly</word>
  <word>breeze</word>
  <word>bright</word>
  <word>brighten</word>
  <word>brighter</word>
  <word>brightest</word>
  <word>brilliance</word>
  <word>brilliances</word>
  <word>brilliant</word>
  <word>brilliantly</word>
  <word>brisk</word>
  <word>brotherly</word>
  <word>bullish</word>
  <word>buoyant</word>
  <word>cajole</word>
  <word>calm</word>
  <word>calming</word>
  <word>calmness</word>
  <word>capability</word>
  <word>capable</word>
  <word>capably</word>
  <word>captivate</word>
  <word>captivating</word>
  <word>carefree</word>
  <word>cashback</word>
  <word>cashbacks</word>
  <word>catchy</word>
  <word>celebrate</word>
  <word>celebrated</word>
  <word>celebration</word>
  <word>celebratory</word>
  <word>champ</word>
  <word>champion</word>
  <word>charisma</word>
  <word>charismatic</word>
  <word>charitable</word>
  <word>charm</word>
  <word>charming</word>
  <word>charmingly</word>
  <word>chaste</word>
  <word>cheaper</word>
  <word>cheapest</word>
  <word>cheer</word>
  <word>cheerful</word>
  <word>cheery</word>
  <word>cherish</word>
  <word>cherished</word>
  <word>cherub</word>
  <word>chic</word>
  <word>chivalrous</word>
  <word>chivalry</word>
  <word>civility</word>
  <word>civilize</word>
  <word>clarity</word>
  <word>classic</word>
  <word>classy</word>
  <word>clean</word>
  <word>cleaner</word>
  <word>cleanest</word>
  <word>cleanliness</word>
  <word>cleanly</word>
  <word>clear</word>
  <word>clear-cut</word>
  <word>cleared</word>
  <word>clearer</word>
  <word>clearly</word>
  <word>clears</word>
  <word>clever</word>
  <word>cleverly</word>
  <word>cohere</word>
  <word>coherence</word>
  <word>coherent</word>
  <word>cohesive</word>
  <word>colorful</word>
  <word>comely</word>
  <word>comfort</word>
  <word>comfortable</word>
  <word>comfortably</word>
  <word>comforting</word>
  <word>comfy</word>
  <word>commend</word>
  <word>commendable</word>
  <word>commendably</word>
  <word>commitment</word>
  <word>commodious</word>
  <word>compact</word>
  <word>compactly</word>
  <word>compassion</word>
  <word>compassionate</word>
  <word>compatible</word>
  <word>competitive</word>
  <word>complement</word>
  <word>complementary</word>
  <word>complemented</word>
  <word>complements</word>
  <word>compliant</word>
  <word>compliment</word>
  <word>complimentary</word>
  <word>comprehensive</word>
  <word>conciliate</word>
  <word>conciliatory</word>
  <word>concise</word>
  <word>confidence</word>
  <word>confident</word>
  <word>congenial</word>
  <word>congratulate</word>
  <word>congratulation</word>
  <word>congratulations</word>
  <word>congratulatory</word>
  <word>conscientious</word>
  <word>considerate</word>
  <word>consistent</word>
  <word>consistently</word>
  <word>constructive</word>
  <word>consummate</word>
  <word>contentment</word>
  <word>continuity</word>
  <word>contrasty</word>
  <word>contribution</word>
  <word>convenience</word>
  <word>convenient</word>
  <word>conveniently</word>
  <word>convience</word>
  <word>convienient</word>
  <word>convient</word>
  <word>convincing</word>
  <word>convincingly</word>
  <word>cool</word>
  <word>coolest</word>
  <word>cooperative</word>
  <word>cooperatively</word>
  <word>cornerstone</word>
  <word>correct</word>
  <word>correctly</word>
  <word>cost-effective</word>
  <word>cost-saving</word>
  <word>counter-attack</word>
  <word>counter-attacks</word>
  <word>courage</word>
  <word>courageous</word>
  <word>courageously</word>
  <word>courageousness</word>
  <word>courteous</word>
  <word>courtly</word>
  <word>covenant</word>
  <word>cozy</word>
  <word>creative</word>
  <word>credence</word>
  <word>credible</word>
  <word>crisp</word>
  <word>crisper</word>
  <word>cure</word>
  <word>cure-all</word>
  <word>cushy</word>
  <word>cute</word>
  <word>cuteness</word>
  <word>danke</word>
  <word>danken</word>
  <word>daring</word>
  <word>daringly</word>
  <word>darling</word>
  <word>dashing</word>
  <word>dauntless</word>
  <word>dawn</word>
  <word>dazzle</word>
  <word>dazzled</word>
  <word>dazzling</word>
  <word>dead-cheap</word>
  <word>dead-on</word>
  <word>decency</word>
  <word>decent</word>
  <word>decisive</word>
  <word>decisiveness</word>
  <word>dedicated</word>
  <word>defeat</word>
  <word>defeated</word>
  <word>defeating</word>
  <word>defeats</word>
  <word>defender</word>
  <word>deference</word>
  <word>deft</word>
  <word>deginified</word>
  <word>delectable</word>
  <word>delicacy</word>
  <word>delicate</word>
  <word>delicious</word>
  <word>delight</word>
  <word>delighted</word>
  <word>delightful</word>
  <word>delightfully</word>
  <word>delightfulness</word>
  <word>dependable</word>
  <word>dependably</word>
  <word>deservedly</word>
  <word>deserving</word>
  <word>desirable</word>
  <word>desiring</word>
  <word>desirous</word>
  <word>destiny</word>
  <word>detachable</word>
  <word>devout</word>
  <word>dexterous</word>
  <word>dexterously</word>
  <word>dextrous</word>
  <word>dignified</word>
  <word>dignify</word>
  <word>dignity</word>
  <word>diligence</word>
  <word>diligent</word>
  <word>diligently</word>
  <word>diplomatic</word>
  <word>dirt-cheap</word>
  <word>distinction</word>
  <word>distinctive</word>
  <word>distinguished</word>
  <word>diversified</word>
  <word>divine</word>
  <word>divinely</word>
  <word>dominate</word>
  <word>dominated</word>
  <word>dominates</word>
  <word>dote</word>
  <word>dotingly</word>
  <word>doubtless</word>
  <word>dreamland</word>
  <word>dumbfounded</word>
  <word>dumbfounding</word>
  <word>dummy-proof</word>
  <word>durable</word>
  <word>dynamic</word>
  <word>eager</word>
  <word>eagerly</word>
  <word>eagerness</word>
  <word>earnest</word>
  <word>earnestly</word>
  <word>earnestness</word>
  <word>ease</word>
  <word>eased</word>
  <word>eases</word>
  <word>easier</word>
  <word>easiest</word>
  <word>easiness</word>
  <word>easing</word>
  <word>easy</word>
  <word>easy-to-use</word>
  <word>easygoing</word>
  <word>ebullience</word>
  <word>ebullient</word>
  <word>ebulliently</word>
  <word>ecenomical</word>
  <word>economical</word>
  <word>ecstasies</word>
  <word>ecstasy</word>
  <word>ecstatic</word>
  <word>ecstatically</word>
  <word>edify</word>
  <word>educated</word>
  <word>effective</word>
  <word>effectively</word>
  <word>effectiveness</word>
  <word>effectual</word>
  <word>efficacious</word>
  <word>efficient</word>
  <word>efficiently</word>
  <word>effortless</word>
  <word>effortlessly</word>
  <word>effusion</word>
  <word>effusive</word>
  <word>effusively</word>
  <word>effusiveness</word>
  <word>elan</word>
  <word>elate</word>
  <word>elated</word>
  <word>elatedly</word>
  <word>elation</word>
  <word>electrify</word>
  <word>elegance</word>
  <word>elegant</word>
  <word>elegantly</word>
  <word>elevate</word>
  <word>elite</word>
  <word>eloquence</word>
  <word>eloquent</word>
  <word>eloquently</word>
  <word>embolden</word>
  <word>eminence</word>
  <word>eminent</word>
  <word>empathize</word>
  <word>empathy</word>
  <word>empower</word>
  <word>empowerment</word>
  <word>enchant</word>
  <word>enchanted</word>
  <word>enchanting</word>
  <word>enchantingly</word>
  <word>encourage</word>
  <word>encouragement</word>
  <word>encouraging</word>
  <word>encouragingly</word>
  <word>endear</word>
  <word>endearing</word>
  <word>endorse</word>
  <word>endorsed</word>
  <word>endorsement</word>
  <word>endorses</word>
  <word>endorsing</word>
  <word>energetic</word>
  <word>energize</word>
  <word>energy-efficient</word>
  <word>energy-saving</word>
  <word>engaging</word>
  <word>engrossing</word>
  <word>enhance</word>
  <word>enhanced</word>
  <word>enhancement</word>
  <word>enhances</word>
  <word>enjoy</word>
  <word>enjoyable</word>
  <word>enjoyably</word>
  <word>enjoyed</word>
  <word>enjoying</word>
  <word>enjoyment</word>
  <word>enjoys</word>
  <word>enlighten</word>
  <word>enlightenment</word>
  <word>enliven</word>
  <word>ennoble</word>
  <word>enough</word>
  <word>enrapt</word>
  <word>enrapture</word>
  <word>enraptured</word>
  <word>enrich</word>
  <word>enrichment</word>
  <word>enterprising</word>
  <word>entertain</word>
  <word>entertaining</word>
  <word>entertains</word>
  <word>enthral</word>
  <word>enthrall</word>
  <word>enthralled</word>
  <word>enthuse</word>
  <word>enthusiasm</word>
  <word>enthusiast</word>
  <word>enthusiastic</word>
  <word>enthusiastically</word>
  <word>entice</word>
  <word>enticed</word>
  <word>enticing</word>
  <word>enticingly</word>
  <word>entranced</word>
  <word>entrancing</word>
  <word>entrust</word>
  <word>enviable</word>
  <word>enviably</word>
  <word>envious</word>
  <word>enviously</word>
  <word>enviousness</word>
  <word>envy</word>
  <word>equitable</word>
  <word>ergonomical</word>
  <word>err-free</word>
  <word>erudite</word>
  <word>ethical</word>
  <word>eulogize</word>
  <word>euphoria</word>
  <word>euphoric</word>
  <word>euphorically</word>
  <word>evaluative</word>
  <word>evenly</word>
  <word>eventful</word>
  <word>everlasting</word>
  <word>evocative</word>
  <word>exalt</word>
  <word>exaltation</word>
  <word>exalted</word>
  <word>exaltedly</word>
  <word>exalting</word>
  <word>exaltingly</word>
  <word>examplar</word>
  <word>examplary</word>
  <word>excallent</word>
  <word>exceed</word>
  <word>exceeded</word>
  <word>exceeding</word>
  <word>exceedingly</word>
  <word>exceeds</word>
  <word>excel</word>
  <word>exceled</word>
  <word>excelent</word>
  <word>excellant</word>
  <word>excelled</word>
  <word>excellence</word>
  <word>excellency</word>
  <word>excellent</word>
  <word>excellently</word>
  <word>excels</word>
  <word>exceptional</word>
  <word>exceptionally</word>
  <word>excite</word>
  <word>excited</word>
  <word>excitedly</word>
  <word>excitedness</word>
  <word>excitement</word>
  <word>excites</word>
  <word>exciting</word>
  <word>excitingly</word>
  <word>exellent</word>
  <word>exemplar</word>
  <word>exemplary</word>
  <word>exhilarate</word>
  <word>exhilarating</word>
  <word>exhilaratingly</word>
  <word>exhilaration</word>
  <word>exonerate</word>
  <word>expansive</word>
  <word>expeditiously</word>
  <word>expertly</word>
  <word>exquisite</word>
  <word>exquisitely</word>
  <word>extol</word>
  <word>extoll</word>
  <word>extraordinarily</word>
  <word>extraordinary</word>
  <word>exuberance</word>
  <word>exuberant</word>
  <word>exuberantly</word>
  <word>exult</word>
  <word>exultant</word>
  <word>exultation</word>
  <word>exultingly</word>
  <word>eye-catch</word>
  <word>eye-catching</word>
  <word>eyecatch</word>
  <word>eyecatching</word>
  <word>fabulous</word>
  <word>fabulously</word>
  <word>facilitate</word>
  <word>fair</word>
  <word>fairly</word>
  <word>fairness</word>
  <word>faith</word>
  <word>faithful</word>
  <word>faithfully</word>
  <word>faithfulness</word>
  <word>fame</word>
  <word>famed</word>
  <word>famous</word>
  <word>famously</word>
  <word>fancier</word>
  <word>fancinating</word>
  <word>fancy</word>
  <word>fanfare</word>
  <word>fans</word>
  <word>fantastic</word>
  <word>fantastically</word>
  <word>fascinate</word>
  <word>fascinating</word>
  <word>fascinatingly</word>
  <word>fascination</word>
  <word>fashionable</word>
  <word>fashionably</word>
  <word>fast</word>
  <word>fast-growing</word>
  <word>fast-paced</word>
  <word>faster</word>
  <word>fastest</word>
  <word>fastest-growing</word>
  <word>faultless</word>
  <word>fav</word>
  <word>fave</word>
  <word>favor</word>
  <word>favorable</word>
  <word>favored</word>
  <word>favorite</word>
  <word>favorited</word>
  <word>favour</word>
  <word>fearless</word>
  <word>fearlessly</word>
  <word>feasible</word>
  <word>feasibly</word>
  <word>feat</word>
  <word>feature-rich</word>
  <word>fecilitous</word>
  <word>feisty</word>
  <word>felicitate</word>
  <word>felicitous</word>
  <word>felicity</word>
  <word>fertile</word>
  <word>fervent</word>
  <word>fervently</word>
  <word>fervid</word>
  <word>fervidly</word>
  <word>fervor</word>
  <word>festive</word>
  <word>fidelity</word>
  <word>fiery</word>
  <word>fine</word>
  <word>fine-looking</word>
  <word>finely</word>
  <word>finer</word>
  <word>finest</word>
  <word>firmer</word>
  <word>first-class</word>
  <word>first-in-class</word>
  <word>first-rate</word>
  <word>flashy</word>
  <word>flatter</word>
  <word>flattering</word>
  <word>flatteringly</word>
  <word>flawless</word>
  <word>flawlessly</word>
  <word>flexibility</word>
  <word>flexible</word>
  <word>flourish</word>
  <word>flourishing</word>
  <word>fluent</word>
  <word>flutter</word>
  <word>fond</word>
  <word>fondly</word>
  <word>fondness</word>
  <word>foolproof</word>
  <word>foremost</word>
  <word>foresight</word>
  <word>formidable</word>
  <word>fortitude</word>
  <word>fortuitous</word>
  <word>fortuitously</word>
  <word>fortunate</word>
  <word>fortunately</word>
  <word>fortune</word>
  <word>fragrant</word>
  <word>free</word>
  <word>freed</word>
  <word>freedom</word>
  <word>freedoms</word>
  <word>fresh</word>
  <word>fresher</word>
  <word>freshest</word>
  <word>friendliness</word>
  <word>friendly</word>
  <word>frolic</word>
  <word>frugal</word>
  <word>fruitful</word>
  <word>ftw</word>
  <word>fulfillment</word>
  <word>fun</word>
  <word>futurestic</word>
  <word>futuristic</word>
  <word>gaiety</word>
  <word>gaily</word>
  <word>gain</word>
  <word>gained</word>
  <word>gainful</word>
  <word>gainfully</word>
  <word>gaining</word>
  <word>gains</word>
  <word>gallant</word>
  <word>gallantly</word>
  <word>galore</word>
  <word>geekier</word>
  <word>geeky</word>
  <word>gem</word>
  <word>gems</word>
  <word>generosity</word>
  <word>generous</word>
  <word>generously</word>
  <word>genial</word>
  <word>genius</word>
  <word>gentle</word>
  <word>gentlest</word>
  <word>genuine</word>
  <word>gifted</word>
  <word>glad</word>
  <word>gladden</word>
  <word>gladly</word>
  <word>gladness</word>
  <word>glamorous</word>
  <word>glee</word>
  <word>gleeful</word>
  <word>gleefully</word>
  <word>glimmer</word>
  <word>glimmering</word>
  <word>glisten</word>
  <word>glistening</word>
  <word>glitter</word>
  <word>glitz</word>
  <word>glorify</word>
  <word>glorious</word>
  <word>gloriously</word>
  <word>glory</word>
  <word>glow</word>
  <word>glowing</word>
  <word>glowingly</word>
  <word>god-given</word>
  <word>god-send</word>
  <word>godlike</word>
  <word>godsend</word>
  <word>gold</word>
  <word>golden</word>
  <word>good</word>
  <word>goodly</word>
  <word>goodness</word>
  <word>goodwill</word>
  <word>goood</word>
  <word>gooood</word>
  <word>gorgeous</word>
  <word>gorgeously</word>
  <word>grace</word>
  <word>graceful</word>
  <word>gracefully</word>
  <word>gracious</word>
  <word>graciously</word>
  <word>graciousness</word>
  <word>grand</word>
  <word>grandeur</word>
  <word>grateful</word>
  <word>gratefully</word>
  <word>gratification</word>
  <word>gratified</word>
  <word>gratifies</word>
  <word>gratify</word>
  <word>gratifying</word>
  <word>gratifyingly</word>
  <word>gratitude</word>
  <word>great</word>
  <word>greatest</word>
  <word>greatness</word>
  <word>grin</word>
  <word>groundbreaking</word>
  <word>guarantee</word>
  <word>guidance</word>
  <word>guiltless</word>
  <word>gumption</word>
  <word>gush</word>
  <word>gusto</word>
  <word>gutsy</word>
  <word>hail</word>
  <word>halcyon</word>
  <word>hale</word>
  <word>hallmark</word>
  <word>hallmarks</word>
  <word>hallowed</word>
  <word>handier</word>
  <word>handily</word>
  <word>hands-down</word>
  <word>handsome</word>
  <word>handsomely</word>
  <word>handy</word>
  <word>happier</word>
  <word>happily</word>
  <word>happiness</word>
  <word>happy</word>
  <word>hard-working</word>
  <word>hardier</word>
  <word>hardy</word>
  <word>harmless</word>
  <word>harmonious</word>
  <word>harmoniously</word>
  <word>harmonize</word>
  <word>harmony</word>
  <word>headway</word>
  <word>heal</word>
  <word>healthful</word>
  <word>healthy</word>
  <word>hearten</word>
  <word>heartening</word>
  <word>heartfelt</word>
  <word>heartily</word>
  <word>heartwarming</word>
  <word>heaven</word>
  <word>heavenly</word>
  <word>helped</word>
  <word>helpful</word>
  <word>helping</word>
  <word>hero</word>
  <word>heroic</word>
  <word>heroically</word>
  <word>heroine</word>
  <word>heroize</word>
  <word>heros</word>
  <word>high-quality</word>
  <word>high-spirited</word>
  <word>hilarious</word>
  <word>holy</word>
  <word>homage</word>
  <word>honest</word>
  <word>honesty</word>
  <word>honor</word>
  <word>honorable</word>
  <word>honored</word>
  <word>honoring</word>
  <word>hooray</word>
  <word>hopeful</word>
  <word>hospitable</word>
  <word>hot</word>
  <word>hotcake</word>
  <word>hotcakes</word>
  <word>hottest</word>
  <word>hug</word>
  <word>humane</word>
  <word>humble</word>
  <word>humility</word>
  <word>humor</word>
  <word>humorous</word>
  <word>humorously</word>
  <word>humour</word>
  <word>humourous</word>
  <word>ideal</word>
  <word>idealize</word>
  <word>ideally</word>
  <word>idol</word>
  <word>idolize</word>
  <word>idolized</word>
  <word>idyllic</word>
  <word>illuminate</word>
  <word>illuminati</word>
  <word>illuminating</word>
  <word>illumine</word>
  <word>illustrious</word>
  <word>ilu</word>
  <word>imaculate</word>
  <word>imaginative</word>
  <word>immaculate</word>
  <word>immaculately</word>
  <word>immense</word>
  <word>impartial</word>
  <word>impartiality</word>
  <word>impartially</word>
  <word>impassioned</word>
  <word>impeccable</word>
  <word>impeccably</word>
  <word>important</word>
  <word>impress</word>
  <word>impressed</word>
  <word>impresses</word>
  <word>impressive</word>
  <word>impressively</word>
  <word>impressiveness</word>
  <word>improve</word>
  <word>improved</word>
  <word>improvement</word>
  <word>improvements</word>
  <word>improves</word>
  <word>improving</word>
  <word>incredible</word>
  <word>incredibly</word>
  <word>indebted</word>
  <word>individualized</word>
  <word>indulgence</word>
  <word>indulgent</word>
  <word>industrious</word>
  <word>inestimable</word>
  <word>inestimably</word>
  <word>inexpensive</word>
  <word>infallibility</word>
  <word>infallible</word>
  <word>infallibly</word>
  <word>influential</word>
  <word>ingenious</word>
  <word>ingeniously</word>
  <word>ingenuity</word>
  <word>ingenuous</word>
  <word>ingenuously</word>
  <word>innocuous</word>
  <word>innovation</word>
  <word>innovative</word>
  <word>inpressed</word>
  <word>insightful</word>
  <word>insightfully</word>
  <word>inspiration</word>
  <word>inspirational</word>
  <word>inspire</word>
  <word>inspiring</word>
  <word>instantly</word>
  <word>instructive</word>
  <word>instrumental</word>
  <word>integral</word>
  <word>integrated</word>
  <word>intelligence</word>
  <word>intelligent</word>
  <word>intelligible</word>
  <word>interesting</word>
  <word>interests</word>
  <word>intimacy</word>
  <word>intimate</word>
  <word>intricate</word>
  <word>intrigue</word>
  <word>intriguing</word>
  <word>intriguingly</word>
  <word>intuitive</word>
  <word>invaluable</word>
  <word>invaluablely</word>
  <word>inventive</word>
  <word>invigorate</word>
  <word>invigorating</word>
  <word>invincibility</word>
  <word>invincible</word>
  <word>inviolable</word>
  <word>inviolate</word>
  <word>invulnerable</word>
  <word>irreplaceable</word>
  <word>irreproachable</word>
  <word>irresistible</word>
  <word>irresistibly</word>
  <word>issue-free</word>
  <word>jaw-droping</word>
  <word>jaw-dropping</word>
  <word>jollify</word>
  <word>jolly</word>
  <word>jovial</word>
  <word>joy</word>
  <word>joyful</word>
  <word>joyfully</word>
  <word>joyous</word>
  <word>joyously</word>
  <word>jubilant</word>
  <word>jubilantly</word>
  <word>jubilate</word>
  <word>jubilation</word>
  <word>jubiliant</word>
  <word>judicious</word>
  <word>justly</word>
  <word>keen</word>
  <word>keenly</word>
  <word>keenness</word>
  <word>kid-friendly</word>
  <word>kindliness</word>
  <word>kindly</word>
  <word>kindness</word>
  <word>knowledgeable</word>
  <word>kudos</word>
  <word>large-capacity</word>
  <word>laud</word>
  <word>laudable</word>
  <word>laudably</word>
  <word>lavish</word>
  <word>lavishly</word>
  <word>law-abiding</word>
  <word>lawful</word>
  <word>lawfully</word>
  <word>lead</word>
  <word>leading</word>
  <word>leads</word>
  <word>lean</word>
  <word>led</word>
  <word>legendary</word>
  <word>leverage</word>
  <word>levity</word>
  <word>liberate</word>
  <word>liberation</word>
  <word>liberty</word>
  <word>lifesaver</word>
  <word>light-hearted</word>
  <word>lighter</word>
  <word>likable</word>
  <word>like</word>
  <word>liked</word>
  <word>likes</word>
  <word>liking</word>
  <word>lionhearted</word>
  <word>lively</word>
  <word>logical</word>
  <word>long-lasting</word>
  <word>lovable</word>
  <word>lovably</word>
  <word>love</word>
  <word>loved</word>
  <word>loveliness</word>
  <word>lovely</word>
  <word>lover</word>
  <word>loves</word>
  <word>loving</word>
  <word>low-cost</word>
  <word>low-price</word>
  <word>low-priced</word>
  <word>low-risk</word>
  <word>lower-priced</word>
  <word>loyal</word>
  <word>loyalty</word>
  <word>lucid</word>
  <word>lucidly</word>
  <word>luck</word>
  <word>luckier</word>
  <word>luckiest</word>
  <word>luckiness</word>
  <word>lucky</word>
  <word>lucrative</word>
  <word>luminous</word>
  <word>lush</word>
  <word>luster</word>
  <word>lustrous</word>
  <word>luxuriant</word>
  <word>luxuriate</word>
  <word>luxurious</word>
  <word>luxuriously</word>
  <word>luxury</word>
  <word>lyrical</word>
  <word>magic</word>
  <word>magical</word>
  <word>magnanimous</word>
  <word>magnanimously</word>
  <word>magnificence</word>
  <word>magnificent</word>
  <word>magnificently</word>
  <word>majestic</word>
  <word>majesty</word>
  <word>manageable</word>
  <word>maneuverable</word>
  <word>marvel</word>
  <word>marveled</word>
  <word>marvelled</word>
  <word>marvellous</word>
  <word>marvelous</word>
  <word>marvelously</word>
  <word>marvelousness</word>
  <word>marvels</word>
  <word>master</word>
  <word>masterful</word>
  <word>masterfully</word>
  <word>masterpiece</word>
  <word>masterpieces</word>
  <word>masters</word>
  <word>mastery</word>
  <word>matchless</word>
  <word>mature</word>
  <word>maturely</word>
  <word>maturity</word>
  <word>meaningful</word>
  <word>memorable</word>
  <word>merciful</word>
  <word>mercifully</word>
  <word>mercy</word>
  <word>merit</word>
  <word>meritorious</word>
  <word>merrily</word>
  <word>merriment</word>
  <word>merriness</word>
  <word>merry</word>
  <word>mesmerize</word>
  <word>mesmerized</word>
  <word>mesmerizes</word>
  <word>mesmerizing</word>
  <word>mesmerizingly</word>
  <word>meticulous</word>
  <word>meticulously</word>
  <word>mightily</word>
  <word>mighty</word>
  <word>mind-blowing</word>
  <word>miracle</word>
  <word>miracles</word>
  <word>miraculous</word>
  <word>miraculously</word>
  <word>miraculousness</word>
  <word>modern</word>
  <word>modest</word>
  <word>modesty</word>
  <word>momentous</word>
  <word>monumental</word>
  <word>monumentally</word>
  <word>morality</word>
  <word>motivated</word>
  <word>multi-purpose</word>
  <word>navigable</word>
  <word>neat</word>
  <word>neatest</word>
  <word>neatly</word>
  <word>nice</word>
  <word>nicely</word>
  <word>nicer</word>
  <word>nicest</word>
  <word>nifty</word>
  <word>nimble</word>
  <word>noble</word>
  <word>nobly</word>
  <word>noiseless</word>
  <word>non-violence</word>
  <word>non-violent</word>
  <word>notably</word>
  <word>noteworthy</word>
  <word>nourish</word>
  <word>nourishing</word>
  <word>nourishment</word>
  <word>novelty</word>
  <word>nurturing</word>
  <word>oasis</word>
  <word>obsession</word>
  <word>obsessions</word>
  <word>obtainable</word>
  <word>openly</word>
  <word>openness</word>
  <word>optimal</word>
  <word>optimism</word>
  <word>optimistic</word>
  <word>opulent</word>
  <word>orderly</word>
  <word>originality</word>
  <word>outdo</word>
  <word>outdone</word>
  <word>outperform</word>
  <word>outperformed</word>
  <word>outperforming</word>
  <word>outperforms</word>
  <word>outshine</word>
  <word>outshone</word>
  <word>outsmart</word>
  <word>outstanding</word>
  <word>outstandingly</word>
  <word>outstrip</word>
  <word>outwit</word>
  <word>ovation</word>
  <word>overjoyed</word>
  <word>overtake</word>
  <word>overtaken</word>
  <word>overtakes</word>
  <word>overtaking</word>
  <word>overtook</word>
  <word>overture</word>
  <word>pain-free</word>
  <word>painless</word>
  <word>painlessly</word>
  <word>palatial</word>
  <word>pamper</word>
  <word>pampered</word>
  <word>pamperedly</word>
  <word>pamperedness</word>
  <word>pampers</word>
  <word>panoramic</word>
  <word>paradise</word>
  <word>paramount</word>
  <word>pardon</word>
  <word>passion</word>
  <word>passionate</word>
  <word>passionately</word>
  <word>patience</word>
  <word>patient</word>
  <word>patiently</word>
  <word>patriot</word>
  <word>patriotic</word>
  <word>peace</word>
  <word>peaceable</word>
  <word>peaceful</word>
  <word>peacefully</word>
  <word>peacekeepers</word>
  <word>peach</word>
  <word>peerless</word>
  <word>pep</word>
  <word>pepped</word>
  <word>pepping</word>
  <word>peppy</word>
  <word>peps</word>
  <word>perfect</word>
  <word>perfection</word>
  <word>perfectly</word>
  <word>permissible</word>
  <word>perseverance</word>
  <word>persevere</word>
  <word>personages</word>
  <word>personalized</word>
  <word>phenomenal</word>
  <word>phenomenally</word>
  <word>picturesque</word>
  <word>piety</word>
  <word>pinnacle</word>
  <word>playful</word>
  <word>playfully</word>
  <word>pleasant</word>
  <word>pleasantly</word>
  <word>pleased</word>
  <word>pleases</word>
  <word>pleasing</word>
  <word>pleasingly</word>
  <word>pleasurable</word>
  <word>pleasurably</word>
  <word>pleasure</word>
  <word>plentiful</word>
  <word>pluses</word>
  <word>plush</word>
  <word>plusses</word>
  <word>poetic</word>
  <word>poeticize</word>
  <word>poignant</word>
  <word>poise</word>
  <word>poised</word>
  <word>polished</word>
  <word>polite</word>
  <word>politeness</word>
  <word>popular</word>
  <word>portable</word>
  <word>posh</word>
  <word>positive</word>
  <word>positively</word>
  <word>positives</word>
  <word>powerful</word>
  <word>powerfully</word>
  <word>praise</word>
  <word>praiseworthy</word>
  <word>praising</word>
  <word>pre-eminent</word>
  <word>precious</word>
  <word>precise</word>
  <word>precisely</word>
  <word>preeminent</word>
  <word>prefer</word>
  <word>preferable</word>
  <word>preferably</word>
  <word>prefered</word>
  <word>preferes</word>
  <word>preferring</word>
  <word>prefers</word>
  <word>premier</word>
  <word>prestige</word>
  <word>prestigious</word>
  <word>prettily</word>
  <word>pretty</word>
  <word>priceless</word>
  <word>pride</word>
  <word>principled</word>
  <word>privilege</word>
  <word>privileged</word>
  <word>prize</word>
  <word>proactive</word>
  <word>problem-free</word>
  <word>problem-solver</word>
  <word>prodigious</word>
  <word>prodigiously</word>
  <word>prodigy</word>
  <word>productive</word>
  <word>productively</word>
  <word>proficient</word>
  <word>proficiently</word>
  <word>profound</word>
  <word>profoundly</word>
  <word>profuse</word>
  <word>profusion</word>
  <word>progress</word>
  <word>progressive</word>
  <word>prolific</word>
  <word>prominence</word>
  <word>prominent</word>
  <word>promise</word>
  <word>promised</word>
  <word>promises</word>
  <word>promising</word>
  <word>promoter</word>
  <word>prompt</word>
  <word>promptly</word>
  <word>proper</word>
  <word>properly</word>
  <word>propitious</word>
  <word>propitiously</word>
  <word>pros</word>
  <word>prosper</word>
  <word>prosperity</word>
  <word>prosperous</word>
  <word>prospros</word>
  <word>protect</word>
  <word>protection</word>
  <word>protective</word>
  <word>proud</word>
  <word>proven</word>
  <word>proves</word>
  <word>providence</word>
  <word>proving</word>
  <word>prowess</word>
  <word>prudence</word>
  <word>prudent</word>
  <word>prudently</word>
  <word>punctual</word>
  <word>pure</word>
  <word>purify</word>
  <word>purposeful</word>
  <word>quaint</word>
  <word>qualified</word>
  <word>qualify</word>
  <word>quicker</word>
  <word>quiet</word>
  <word>quieter</word>
  <word>radiance</word>
  <word>radiant</word>
  <word>rapid</word>
  <word>rapport</word>
  <word>rapt</word>
  <word>rapture</word>
  <word>raptureous</word>
  <word>raptureously</word>
  <word>rapturous</word>
  <word>rapturously</word>
  <word>rational</word>
  <word>razor-sharp</word>
  <word>reachable</word>
  <word>readable</word>
  <word>readily</word>
  <word>ready</word>
  <word>reaffirm</word>
  <word>reaffirmation</word>
  <word>realistic</word>
  <word>realizable</word>
  <word>reasonable</word>
  <word>reasonably</word>
  <word>reasoned</word>
  <word>reassurance</word>
  <word>reassure</word>
  <word>receptive</word>
  <word>reclaim</word>
  <word>recomend</word>
  <word>recommend</word>
  <word>recommendation</word>
  <word>recommendations</word>
  <word>recommended</word>
  <word>reconcile</word>
  <word>reconciliation</word>
  <word>record-setting</word>
  <word>recover</word>
  <word>recovery</word>
  <word>rectification</word>
  <word>rectify</word>
  <word>rectifying</word>
  <word>redeem</word>
  <word>redeeming</word>
  <word>redemption</word>
  <word>refine</word>
  <word>refined</word>
  <word>refinement</word>
  <word>reform</word>
  <word>reformed</word>
  <word>reforming</word>
  <word>reforms</word>
  <word>refresh</word>
  <word>refreshed</word>
  <word>refreshing</word>
  <word>refund</word>
  <word>refunded</word>
  <word>regal</word>
  <word>regally</word>
  <word>regard</word>
  <word>rejoice</word>
  <word>rejoicing</word>
  <word>rejoicingly</word>
  <word>rejuvenate</word>
  <word>rejuvenated</word>
  <word>rejuvenating</word>
  <word>relaxed</word>
  <word>relent</word>
  <word>reliable</word>
  <word>reliably</word>
  <word>relief</word>
  <word>relish</word>
  <word>remarkable</word>
  <word>remarkably</word>
  <word>remedy</word>
  <word>remission</word>
  <word>remunerate</word>
  <word>renaissance</word>
  <word>renewed</word>
  <word>renown</word>
  <word>renowned</word>
  <word>replaceable</word>
  <word>reputable</word>
  <word>reputation</word>
  <word>resilient</word>
  <word>resolute</word>
  <word>resound</word>
  <word>resounding</word>
  <word>resourceful</word>
  <word>resourcefulness</word>
  <word>respect</word>
  <word>respectable</word>
  <word>respectful</word>
  <word>respectfully</word>
  <word>respite</word>
  <word>resplendent</word>
  <word>responsibly</word>
  <word>responsive</word>
  <word>restful</word>
  <word>restored</word>
  <word>restructure</word>
  <word>restructured</word>
  <word>restructuring</word>
  <word>retractable</word>
  <word>revel</word>
  <word>revelation</word>
  <word>revere</word>
  <word>reverence</word>
  <word>reverent</word>
  <word>reverently</word>
  <word>revitalize</word>
  <word>revival</word>
  <word>revive</word>
  <word>revives</word>
  <word>revolutionary</word>
  <word>revolutionize</word>
  <word>revolutionized</word>
  <word>revolutionizes</word>
  <word>reward</word>
  <word>rewarding</word>
  <word>rewardingly</word>
  <word>rich</word>
  <word>richer</word>
  <word>richly</word>
  <word>richness</word>
  <word>right</word>
  <word>righten</word>
  <word>righteous</word>
  <word>righteously</word>
  <word>righteousness</word>
  <word>rightful</word>
  <word>rightfully</word>
  <word>rightly</word>
  <word>rightness</word>
  <word>risk-free</word>
  <word>robust</word>
  <word>rock-star</word>
  <word>rock-stars</word>
  <word>rockstar</word>
  <word>rockstars</word>
  <word>romantic</word>
  <word>romantically</word>
  <word>romanticize</word>
  <word>roomier</word>
  <word>roomy</word>
  <word>rosy</word>
  <word>safe</word>
  <word>safely</word>
  <word>sagacity</word>
  <word>sagely</word>
  <word>saint</word>
  <word>saintliness</word>
  <word>saintly</word>
  <word>salutary</word>
  <word>salute</word>
  <word>sane</word>
  <word>satisfactorily</word>
  <word>satisfactory</word>
  <word>satisfied</word>
  <word>satisfies</word>
  <word>satisfy</word>
  <word>satisfying</word>
  <word>satisified</word>
  <word>saver</word>
  <word>savings</word>
  <word>savior</word>
  <word>savvy</word>
  <word>scenic</word>
  <word>seamless</word>
  <word>seasoned</word>
  <word>secure</word>
  <word>securely</word>
  <word>selective</word>
  <word>self-determination</word>
  <word>self-respect</word>
  <word>self-satisfaction</word>
  <word>self-sufficiency</word>
  <word>self-sufficient</word>
  <word>sensation</word>
  <word>sensational</word>
  <word>sensationally</word>
  <word>sensations</word>
  <word>sensible</word>
  <word>sensibly</word>
  <word>sensitive</word>
  <word>serene</word>
  <word>serenity</word>
  <word>sexy</word>
  <word>sharp</word>
  <word>sharper</word>
  <word>sharpest</word>
  <word>shimmering</word>
  <word>shimmeringly</word>
  <word>shine</word>
  <word>shiny</word>
  <word>significant</word>
  <word>silent</word>
  <word>simpler</word>
  <word>simplest</word>
  <word>simplified</word>
  <word>simplifies</word>
  <word>simplify</word>
  <word>simplifying</word>
  <word>sincere</word>
  <word>sincerely</word>
  <word>sincerity</word>
  <word>skill</word>
  <word>skilled</word>
  <word>skillful</word>
  <word>skillfully</word>
  <word>slammin</word>
  <word>sleek</word>
  <word>slick</word>
  <word>smart</word>
  <word>smarter</word>
  <word>smartest</word>
  <word>smartly</word>
  <word>smile</word>
  <word>smiles</word>
  <word>smiling</word>
  <word>smilingly</word>
  <word>smitten</word>
  <word>smooth</word>
  <word>smoother</word>
  <word>smoothes</word>
  <word>smoothest</word>
  <word>smoothly</word>
  <word>snappy</word>
  <word>snazzy</word>
  <word>sociable</word>
  <word>soft</word>
  <word>softer</word>
  <word>solace</word>
  <word>solicitous</word>
  <word>solicitously</word>
  <word>solid</word>
  <word>solidarity</word>
  <word>soothe</word>
  <word>soothingly</word>
  <word>sophisticated</word>
  <word>soulful</word>
  <word>soundly</word>
  <word>soundness</word>
  <word>spacious</word>
  <word>sparkle</word>
  <word>sparkling</word>
  <word>spectacular</word>
  <word>spectacularly</word>
  <word>speedily</word>
  <word>speedy</word>
  <word>spellbind</word>
  <word>spellbinding</word>
  <word>spellbindingly</word>
  <word>spellbound</word>
  <word>spirited</word>
  <word>spiritual</word>
  <word>splendid</word>
  <word>splendidly</word>
  <word>splendor</word>
  <word>spontaneous</word>
  <word>sporty</word>
  <word>spotless</word>
  <word>sprightly</word>
  <word>stability</word>
  <word>stabilize</word>
  <word>stable</word>
  <word>stainless</word>
  <word>standout</word>
  <word>state-of-the-art</word>
  <word>stately</word>
  <word>statuesque</word>
  <word>staunch</word>
  <word>staunchly</word>
  <word>staunchness</word>
  <word>steadfast</word>
  <word>steadfastly</word>
  <word>steadfastness</word>
  <word>steadiest</word>
  <word>steadiness</word>
  <word>steady</word>
  <word>stellar</word>
  <word>stellarly</word>
  <word>stimulate</word>
  <word>stimulates</word>
  <word>stimulating</word>
  <word>stimulative</word>
  <word>stirringly</word>
  <word>straighten</word>
  <word>straightforward</word>
  <word>streamlined</word>
  <word>striking</word>
  <word>strikingly</word>
  <word>striving</word>
  <word>strong</word>
  <word>stronger</word>
  <word>strongest</word>
  <word>stunned</word>
  <word>stunning</word>
  <word>stunningly</word>
  <word>stupendous</word>
  <word>stupendously</word>
  <word>sturdier</word>
  <word>sturdy</word>
  <word>stylish</word>
  <word>stylishly</word>
  <word>stylized</word>
  <word>suave</word>
  <word>suavely</word>
  <word>sublime</word>
  <word>subsidize</word>
  <word>subsidized</word>
  <word>subsidizes</word>
  <word>subsidizing</word>
  <word>substantive</word>
  <word>succeed</word>
  <word>succeeded</word>
  <word>succeeding</word>
  <word>succeeds</word>
  <word>succes</word>
  <word>success</word>
  <word>successes</word>
  <word>successful</word>
  <word>successfully</word>
  <word>suffice</word>
  <word>sufficed</word>
  <word>suffices</word>
  <word>sufficient</word>
  <word>sufficiently</word>
  <word>suitable</word>
  <word>sumptuous</word>
  <word>sumptuously</word>
  <word>sumptuousness</word>
  <word>super</word>
  <word>superb</word>
  <word>superbly</word>
  <word>superior</word>
  <word>superiority</word>
  <word>supple</word>
  <word>support</word>
  <word>supported</word>
  <word>supporter</word>
  <word>supporting</word>
  <word>supportive</word>
  <word>supports</word>
  <word>supremacy</word>
  <word>supreme</word>
  <word>supremely</word>
  <word>supurb</word>
  <word>supurbly</word>
  <word>surmount</word>
  <word>surpass</word>
  <word>surreal</word>
  <word>survival</word>
  <word>survivor</word>
  <word>sustainability</word>
  <word>sustainable</word>
  <word>swank</word>
  <word>swankier</word>
  <word>swankiest</word>
  <word>swanky</word>
  <word>sweeping</word>
  <word>sweet</word>
  <word>sweeten</word>
  <word>sweetheart</word>
  <word>sweetly</word>
  <word>sweetness</word>
  <word>swift</word>
  <word>swiftness</word>
  <word>talent</word>
  <word>talented</word>
  <word>talents</word>
  <word>tantalize</word>
  <word>tantalizing</word>
  <word>tantalizingly</word>
  <word>tempt</word>
  <word>tempting</word>
  <word>temptingly</word>
  <word>tenacious</word>
  <word>tenaciously</word>
  <word>tenacity</word>
  <word>tender</word>
  <word>tenderly</word>
  <word>terrific</word>
  <word>terrifically</word>
  <word>thank</word>
  <word>thankful</word>
  <word>thinner</word>
  <word>thoughtful</word>
  <word>thoughtfully</word>
  <word>thoughtfulness</word>
  <word>thrift</word>
  <word>thrifty</word>
  <word>thrill</word>
  <word>thrilled</word>
  <word>thrilling</word>
  <word>thrillingly</word>
  <word>thrills</word>
  <word>thrive</word>
  <word>thriving</word>
  <word>thumb-up</word>
  <word>thumbs-up</word>
  <word>tickle</word>
  <word>tidy</word>
  <word>time-honored</word>
  <word>timely</word>
  <word>tingle</word>
  <word>titillate</word>
  <word>titillating</word>
  <word>titillatingly</word>
  <word>togetherness</word>
  <word>tolerable</word>
  <word>toll-free</word>
  <word>top</word>
  <word>top-notch</word>
  <word>top-quality</word>
  <word>topnotch</word>
  <word>tops</word>
  <word>tough</word>
  <word>tougher</word>
  <word>toughest</word>
  <word>traction</word>
  <word>tranquil</word>
  <word>tranquility</word>
  <word>transparent</word>
  <word>treasure</word>
  <word>tremendously</word>
  <word>trendy</word>
  <word>triumph</word>
  <word>triumphal</word>
  <word>triumphant</word>
  <word>triumphantly</word>
  <word>trivially</word>
  <word>trophy</word>
  <word>trouble-free</word>
  <word>trump</word>
  <word>trumpet</word>
  <word>trust</word>
  <word>trusted</word>
  <word>trusting</word>
  <word>trustingly</word>
  <word>trustworthiness</word>
  <word>trustworthy</word>
  <word>trusty</word>
  <word>truthful</word>
  <word>truthfully</word>
  <word>truthfulness</word>
  <word>twinkly</word>
  <word>ultra-crisp</word>
  <word>unabashed</word>
  <word>unabashedly</word>
  <word>unaffected</word>
  <word>unassailable</word>
  <word>unbeatable</word>
  <word>unbiased</word>
  <word>unbound</word>
  <word>uncomplicated</word>
  <word>unconditional</word>
  <word>undamaged</word>
  <word>undaunted</word>
  <word>understandable</word>
  <word>undisputable</word>
  <word>undisputably</word>
  <word>undisputed</word>
  <word>unencumbered</word>
  <word>unequivocal</word>
  <word>unequivocally</word>
  <word>unfazed</word>
  <word>unfettered</word>
  <word>unforgettable</word>
  <word>unity</word>
  <word>unlimited</word>
  <word>unmatched</word>
  <word>unparalleled</word>
  <word>unquestionable</word>
  <word>unquestionably</word>
  <word>unreal</word>
  <word>unrestricted</word>
  <word>unrivaled</word>
  <word>unselfish</word>
  <word>unwavering</word>
  <word>upbeat</word>
  <word>upgradable</word>
  <word>upgradeable</word>
  <word>upgraded</word>
  <word>upheld</word>
  <word>uphold</word>
  <word>uplift</word>
  <word>uplifting</word>
  <word>upliftingly</word>
  <word>upliftment</word>
  <word>upscale</word>
  <word>usable</word>
  <word>useable</word>
  <word>useful</word>
  <word>user-friendly</word>
  <word>user-replaceable</word>
  <word>valiant</word>
  <word>valiantly</word>
  <word>valor</word>
  <word>valuable</word>
  <word>variety</word>
  <word>venerate</word>
  <word>verifiable</word>
  <word>veritable</word>
  <word>versatile</word>
  <word>versatility</word>
  <word>vibrant</word>
  <word>vibrantly</word>
  <word>victorious</word>
  <word>victory</word>
  <word>viewable</word>
  <word>vigilance</word>
  <word>vigilant</word>
  <word>virtue</word>
  <word>virtuous</word>
  <word>virtuously</word>
  <word>visionary</word>
  <word>vivacious</word>
  <word>vivid</word>
  <word>vouch</word>
  <word>vouchsafe</word>
  <word>warm</word>
  <word>warmer</word>
  <word>warmhearted</word>
  <word>warmly</word>
  <word>warmth</word>
  <word>wealthy</word>
  <word>welcome</word>
  <word>well</word>
  <word>well-backlit</word>
  <word>well-balanced</word>
  <word>well-behaved</word>
  <word>well-being</word>
  <word>well-bred</word>
  <word>well-connected</word>
  <word>well-educated</word>
  <word>well-established</word>
  <word>well-informed</word>
  <word>well-intentioned</word>
  <word>well-known</word>
  <word>well-made</word>
  <word>well-managed</word>
  <word>well-mannered</word>
  <word>well-positioned</word>
  <word>well-received</word>
  <word>well-regarded</word>
  <word>well-rounded</word>
  <word>well-run</word>
  <word>well-wishers</word>
  <word>wellbeing</word>
  <word>whoa</word>
  <word>wholeheartedly</word>
  <word>wholesome</word>
  <word>whooa</word>
  <word>whoooa</word>
  <word>wieldy</word>
  <word>willing</word>
  <word>willingly</word>
  <word>willingness</word>
  <word>win</word>
  <word>windfall</word>
  <word>winnable</word>
  <word>winner</word>
  <word>winners</word>
  <word>winning</word>
  <word>wins</word>
  <word>wisdom</word>
  <word>wise</word>
  <word>wisely</word>
  <word>witty</word>
  <word>won</word>
  <word>wonder</word>
  <word>wonderful</word>
  <word>wonderfully</word>
  <word>wonderous</word>
  <word>wonderously</word>
  <word>wonders</word>
  <word>wondrous</word>
  <word>woo</word>
  <word>work</word>
  <word>workable</word>
  <word>worked</word>
  <word>works</word>
  <word>world-famous</word>
  <word>worth</word>
  <word>worth-while</word>
  <word>worthiness</word>
  <word>worthwhile</word>
  <word>worthy</word>
  <word>wow</word>
  <word>wowed</word>
  <word>wowing</word>
  <word>wows</word>
  <word>yay</word>
  <word>youthful</word>
  <word>zeal</word>
  <word>zenith</word>
  <word>zest</word>
  <word>zippy</word>
</words>